cjlutils/AdbUtil.py
cjlutils/BytesUtil.py
cjlutils/DictUtil.py
cjlutils/EncodeUtil.py
cjlutils/FileUtil.py
cjlutils/FtpUtil.py
cjlutils/GitUtil.py
cjlutils/HttpUtil.py
cjlutils/LipoUtil.py
cjlutils/ListUtil.py
cjlutils/LogicUtil.py
cjlutils/PyplotUtil.py
cjlutils/ScpUtil.py
cjlutils/SoundUtil.py
cjlutils/SshUtil.py
cjlutils/StringUtil.py
cjlutils/TimeUtil.py
cjlutils/__init__.py
base_tools-0.1.9.dist-info/METADATA
base_tools-0.1.9.dist-info/WHEEL
base_tools-0.1.9.dist-info/licenses/LICENSE
base_tools-0.1.9.dist-info/RECORD
