Metadata-Version: 2.4
Name: base-tools
Version: 0.1.9
Summary: base tools of cjl
Project-URL: Homepage, https://gitee.com/AuspiciousChan/base-tools
Project-URL: Issues, https://gitee.com/AuspiciousChan/base-tools/issues
Author-email: AuspiciousChan <AuspiciousChan@163.com>
License-File: LICENSE
Classifier: License :: OSI Approved :: MIT License
Classifier: Operating System :: OS Independent
Classifier: Programming Language :: Python :: 3
Requires-Python: >=3.10
